.gitignore
.pre-commit-config.yaml
LICENSE
README.rst
setup.py
biscuit/__init__.py
biscuit/__main__.py
biscuit/_version.py
biscuit_py_prima.egg-info/PKG-INFO
biscuit_py_prima.egg-info/SOURCES.txt
biscuit_py_prima.egg-info/dependency_links.txt
biscuit_py_prima.egg-info/entry_points.txt
biscuit_py_prima.egg-info/not-zip-safe
biscuit_py_prima.egg-info/requires.txt
biscuit_py_prima.egg-info/top_level.txt
tests/__init__.py
tests/biscuit_test.py
tests/hello.yaml